grip/__init__.py
grip/fitting.py
grip/generic.py
grip/histogram_tools.py
grip/instrument_models.py
grip/load_files.py
grip/npe.py
grip/plots.py
grip/preprocessing.py
grip_nulling-1.5.1.dist-info/LICENSE
grip_nulling-1.5.1.dist-info/METADATA
grip_nulling-1.5.1.dist-info/WHEEL
grip_nulling-1.5.1.dist-info/top_level.txt
grip_nulling-1.5.1.dist-info/RECORD
