Metadata-Version: 2.2
Name: grip-nulling
Version: 1.5.1
Summary: Self-calibration data reduction tools for nulling interferometry
Author: M.-A. Martinod
License-File: LICENSE
Requires-Dist: numpy>=1.26.2
Requires-Dist: scipy>=1.11.4
Requires-Dist: matplotlib>=3.6.3
Requires-Dist: h5py>=3.8.0
Requires-Dist: emcee>=3.1.4
Requires-Dist: numdifftools>=0.9.41
Requires-Dist: astropy>=5.2.1
Dynamic: author
Dynamic: description
Dynamic: requires-dist
Dynamic: summary
